bycycle/__init__.py
bycycle/version.py
bycycle/burst/__init__.py
bycycle/burst/amp.py
bycycle/burst/cycle.py
bycycle/burst/dualthresh.py
bycycle/burst/utils.py
bycycle/cyclepoints/__init__.py
bycycle/cyclepoints/extrema.py
bycycle/cyclepoints/phase.py
bycycle/cyclepoints/zerox.py
bycycle/features/__init__.py
bycycle/features/burst.py
bycycle/features/cyclepoints.py
bycycle/features/features.py
bycycle/features/shape.py
bycycle/group/__init__.py
bycycle/group/features.py
bycycle/group/utils.py
bycycle/objs/__init__.py
bycycle/objs/fit.py
bycycle/plts/__init__.py
bycycle/plts/burst.py
bycycle/plts/cyclepoints.py
bycycle/plts/features.py
bycycle/recon/__init__.py
bycycle/recon/defaults.py
bycycle/recon/recon_obj.py
bycycle/tests/__init__.py
bycycle/tests/conftest.py
bycycle/tests/settings.py
bycycle/tests/test_persistence.py
bycycle/tests/tutils.py
bycycle/tests/burst/__init__.py
bycycle/tests/burst/test_amp.py
bycycle/tests/burst/test_cycle.py
bycycle/tests/burst/test_utils.py
bycycle/tests/cyclepoints/__init__.py
bycycle/tests/cyclepoints/test_extrema.py
bycycle/tests/cyclepoints/test_phase.py
bycycle/tests/cyclepoints/test_zerox.py
bycycle/tests/features/__init__.py
bycycle/tests/features/test_burst.py
bycycle/tests/features/test_cyclepoints.py
bycycle/tests/features/test_features.py
bycycle/tests/features/test_shapes.py
bycycle/tests/group/__init__.py
bycycle/tests/group/test_features.py
bycycle/tests/group/test_utils.py
bycycle/tests/objs/__init__.py
bycycle/tests/objs/test_fit.py
bycycle/tests/plts/__init__.py
bycycle/tests/plts/test_burst.py
bycycle/tests/plts/test_cyclepoints.py
bycycle/tests/plts/test_features.py
bycycle/tests/utils/__init__.py
bycycle/tests/utils/test_dataframes.py
bycycle/tests/utils/test_download.py
bycycle/tests/utils/test_timeseries.py
bycycle/utils/__init__.py
bycycle/utils/checks.py
bycycle/utils/dataframes.py
bycycle/utils/download.py
bycycle/utils/timeseries.py
bycycle-1.2.0.dist-info/licenses/LICENSE
bycycle-1.2.0.dist-info/METADATA
bycycle-1.2.0.dist-info/WHEEL
bycycle-1.2.0.dist-info/top_level.txt
bycycle-1.2.0.dist-info/RECORD
