Metadata-Version: 2.4
Name: bycycle
Version: 1.2.0
Summary: Cycle-by-cycle analyses of neural oscillations.
Home-page: https://github.com/bycycle-tools/bycycle
Download-URL: https://github.com/bycycle-tools/bycycle/releases
Author: The Voytek Lab
Author-email: voyteklab@gmail.com
License: Apache License, 2.0
Project-URL: Documentation, https://bycycle-tools.github.io/bycycle/
Project-URL: Bug Reports, https://github.com/bycycle-tools/bycycle/issues
Project-URL: Source, https://github.com/bycycle-tools/bycycle
Keywords: neuroscience,neural oscillations,waveform,shape,electrophysiology
Platform: any
Classifier: Development Status :: 4 - Beta
Classifier: Intended Audience :: Science/Research
Classifier: Topic :: Scientific/Engineering
Classifier: License :: OSI Approved :: Apache Software License
Classifier: Operating System :: Microsoft :: Windows
Classifier: Operating System :: MacOS
Classifier: Operating System :: POSIX
Classifier: Operating System :: Unix
Classifier: Programming Language :: Python
Classifier: Programming Language :: Python :: 3.7
Classifier: Programming Language :: Python :: 3.8
Classifier: Programming Language :: Python :: 3.9
Classifier: Programming Language :: Python :: 3.10
Classifier: Programming Language :: Python :: 3.11
Classifier: Programming Language :: Python :: 3.12
Classifier: Programming Language :: Python :: 3.13
Requires-Python: >=3.7
License-File: LICENSE
Requires-Dist: numpy>=1.18.5
Requires-Dist: scipy>=1.4.1
Requires-Dist: pandas>=0.25.3
Requires-Dist: matplotlib>=3.0.3
Requires-Dist: neurodsp>=2.2.1
Dynamic: author
Dynamic: author-email
Dynamic: classifier
Dynamic: description
Dynamic: description-content-type
Dynamic: download-url
Dynamic: home-page
Dynamic: keywords
Dynamic: license
Dynamic: license-file
Dynamic: platform
Dynamic: project-url
Dynamic: requires-dist
Dynamic: requires-python
Dynamic: summary
